setup.py
bin/q
quantize/__init__.py
quantize.egg-info/PKG-INFO
quantize.egg-info/SOURCES.txt
quantize.egg-info/dependency_links.txt
quantize.egg-info/requires.txt
quantize.egg-info/top_level.txt