Metadata-Version: 1.1
Name: quantize
Version: 0.0.3
Summary: A simple command line utility for syncing arbitrary messages sent via `stdin` to a midi clock.
Home-page: https://github.com/abelsonlive/quantize
Author: Brian Abelson
Author-email: brianabelson@gmail.com
License: MIT
Keywords: midi,midi clock,command line
Platform: UNKNOWN
Classifier: Development Status :: 3 - Alpha
Classifier: Topic :: Communications :: Email
Classifier: License :: OSI Approved :: MIT License
